setup.py
OSolntseva_client.egg-info/PKG-INFO
OSolntseva_client.egg-info/SOURCES.txt
OSolntseva_client.egg-info/dependency_links.txt
OSolntseva_client.egg-info/requires.txt
OSolntseva_client.egg-info/top_level.txt
client/__init__.py
client/my_client.py
client/client/__init__.py
client/client/add_contact.py
client/client/client_database.py
client/client/delete_contact.py
client/client/main_window.py
client/client/main_window_conv.py
client/client/start_dialog.py
client/client/transport.py
client/logs/__init__.py
client/logs/client_log_config.py
client/logs/server_log_config.py
client/logs/configs/__init__.py
client/logs/configs/client_log_config.py
client/logs/configs/server_log_config.py
client/project_unittests/__init__.py