Metadata-Version: 1.0
Name: OSolntseva-client
Version: 0.0.1
Summary: OSolntseva_client
Home-page: UNKNOWN
Author: Olga Solntseva
Author-email: w-j-olga24@mail.ru
License: UNKNOWN
Platform: UNKNOWN
